qrcode_plus.py
qrcode_plus-3.1.5.dist-info/entry_points.txt
qrcode_plus-3.1.5.dist-info/LICENSE
qrcode_plus-3.1.5.dist-info/WHEEL
qrcode_plus-3.1.5.dist-info/METADATA
qrcode_plus-3.1.5.dist-info/RECORD
