Metadata-Version: 2.1
Name: qrcode-plus
Version: 3.1.5
Summary: Advance Artistic (Micro) QR Code plugin for Segno
Keywords: QR Code,Micro QR Code,ISO/IEC 18004,ISO/IEC 18004:2006(E),ISO/IEC 18004:2015(E),qrcode,QR,barcode,matrix,2D
Author-email: Kyle Bradley <kbradley53@gmail.com>
Requires-Python: >= 3.5
Classifier: Development Status :: 4 - Beta
Classifier: Intended Audience :: Developers
Classifier: License :: OSI Approved :: BSD License
Classifier: Operating System :: OS Independent
Classifier: Programming Language :: Python
Classifier: Programming Language :: Python :: 3
Classifier: Programming Language :: Python :: 3.7
Classifier: Programming Language :: Python :: 3.8
Classifier: Programming Language :: Python :: 3.9
Classifier: Programming Language :: Python :: 3.10
Classifier: Programming Language :: Python :: 3.11
Classifier: Programming Language :: Python :: 3.12
Classifier: Topic :: Multimedia :: Graphics
Classifier: Topic :: Printing
Classifier: Topic :: Software Development :: Libraries :: Python Modules
Classifier: Topic :: Utilities
Requires-Dist: segno>=1.0.2
Requires-Dist: Pillow
Requires-Dist: cairosvg ; extra == "svg"
Project-URL: Changelog, https://github.com/heuer/qrcode-artistic/blob/master/CHANGES.rst
Project-URL: Documentation, https://segno.readthedocs.io/en/latest/artistic-qrcodes.html
Project-URL: Homepage, https://github.com/heuer/qrcode-artistic/
Project-URL: Issue Tracker, https://github.com/heuer/qrcode-artistic/issues
Project-URL: Repository, https://github.com/heuer/qrcode-artistic.git
Provides-Extra: svg
